justpfm/__init__.py
justpfm/justpfm.py
justpfm-1.0.0.dist-info/LICENSE
justpfm-1.0.0.dist-info/METADATA
justpfm-1.0.0.dist-info/WHEEL
justpfm-1.0.0.dist-info/top_level.txt
justpfm-1.0.0.dist-info/RECORD
