Metadata-Version: 2.1
Name: justpfm
Version: 1.0.0
Summary: Read and write PFM files
Home-page: https://github.com/MartinPeris/justPFM
Author: Martin Peris Martorell
Author-email: cosmoperis@gmail.com
Project-URL: Bug Reports, https://github.com/MartinPeris/justPFM/issues
Project-URL: Source, https://github.com/MartinPeris/justPFM
Keywords: pfm,portable,float,map
Classifier: Development Status :: 5 - Production/Stable
Classifier: Intended Audience :: Science/Research
Classifier: Topic :: Scientific/Engineering :: Image Processing
Classifier: License :: OSI Approved :: MIT License
Classifier: Programming Language :: Python :: 3
Classifier: Programming Language :: Python :: 3.7
Classifier: Programming Language :: Python :: 3.8
Classifier: Programming Language :: Python :: 3.9
Classifier: Programming Language :: Python :: 3.10
Classifier: Programming Language :: Python :: 3 :: Only
Requires-Python: >=3.7, <4
License-File: LICENSE
Requires-Dist: numpy
Provides-Extra: dev
Requires-Dist: check-manifest ; extra == 'dev'
Provides-Extra: test
Requires-Dist: pytest ; extra == 'test'
Requires-Dist: pytest-cov ; extra == 'test'
